Metadata-Version: 1.1
Name: goodbyeworld
Version: 0.0.1
Summary: I want to die
Home-page: UNKNOWN
Author: Ur mom
Author-email: fakeemail@gmail.com
License: UNKNOWN
Platform: UNKNOWN
Classifier: Development Status :: 5 - Production/Stable
Classifier: Intended Audience :: Education
Classifier: Operating System :: MacOS
Classifier: License :: OSI Approved :: MIT License
Classifier: Programming Language :: Python :: 3
